asockit/__about__.py
asockit/__init__.py
asockit/connection.py
asockit/py.typed
asockit/reader.py
asockit/writer.py
asockit/abc/__init__.py
asockit/abc/connection.py
asockit-0.1.1.dist-info/METADATA
asockit-0.1.1.dist-info/WHEEL
asockit-0.1.1.dist-info/licenses/LICENSE
asockit-0.1.1.dist-info/RECORD
